auth_middleware/__init__.py
auth_middleware/auth_provider.py
auth_middleware/basic_auth_middleware.py
auth_middleware/cli.py
auth_middleware/functions.py
auth_middleware/group_checker.py
auth_middleware/jwt_auth_middleware.py
auth_middleware/jwt_bearer_manager.py
auth_middleware/logging.py
auth_middleware/permissions_checker.py
auth_middleware/settings.py
auth_middleware/commands/__init__.py
auth_middleware/exceptions/__init__.py
auth_middleware/exceptions/invalid_authorization_exception.py
auth_middleware/exceptions/invalid_credentials_exception.py
auth_middleware/exceptions/invalid_token_exception.py
auth_middleware/providers/__init__.py
auth_middleware/providers/authn/__init__.py
auth_middleware/providers/authn/cognito_authz_provider_settings.py
auth_middleware/providers/authn/cognito_provider.py
auth_middleware/providers/authn/identity_pool_client.py
auth_middleware/providers/authn/identity_pool_provider.py
auth_middleware/providers/authn/identity_pool_settings.py
auth_middleware/providers/authn/jwt_provider.py
auth_middleware/providers/authn/jwt_provider_settings.py
auth_middleware/providers/authz/__init__.py
auth_middleware/providers/authz/async_database.py
auth_middleware/providers/authz/async_database_settings.py
auth_middleware/providers/authz/cognito_groups_provider.py
auth_middleware/providers/authz/groups_provider.py
auth_middleware/providers/authz/permissions_provider.py
auth_middleware/providers/authz/sql_base_model.py
auth_middleware/providers/authz/sql_groups_provider.py
auth_middleware/providers/authz/sql_permissions_provider.py
auth_middleware/providers/cognito/__init__.py
auth_middleware/providers/cognito/utils.py
auth_middleware/providers/entra_id/__init__.py
auth_middleware/providers/entra_id/entra_id_provider.py
auth_middleware/providers/entra_id/settings.py
auth_middleware/providers/entra_id/utils.py
auth_middleware/providers/exceptions/aws_exception.py
auth_middleware/providers/exceptions/azure_exception.py
auth_middleware-0.2.17.dist-info/METADATA
auth_middleware-0.2.17.dist-info/WHEEL
auth_middleware-0.2.17.dist-info/entry_points.txt
auth_middleware-0.2.17.dist-info/licenses/LICENSE
auth_middleware-0.2.17.dist-info/RECORD
