Metadata-Version: 2.4
Name: auth-middleware
Version: 0.2.17
Summary: Async Auth Middleware for FastAPI/Starlette
Project-URL: Homepage, https://impalah.github.io/auth-middleware/
Project-URL: Documentation, https://impalah.github.io/auth-middleware/
Project-URL: Repository, https://github.com/impalah/auth-middleware
Project-URL: Source, https://github.com/impalah/auth-middleware
Author-email: impalah <impalah@gmail.com>
License: MIT
License-File: LICENSE
Keywords: auth,fastapi,middleware,starlette
Classifier: Development Status :: 4 - Beta
Classifier: Framework :: FastAPI
Classifier: Intended Audience :: Developers
Classifier: License :: OSI Approved :: MIT License
Classifier: Programming Language :: Python :: 3
Classifier: Topic :: Software Development :: Libraries :: Python Modules
Classifier: Topic :: System :: Systems Administration :: Authentication/Directory
Requires-Python: >=3.14
Requires-Dist: aiomysql>=0.3.2
Requires-Dist: asyncpg>=0.31.0
Requires-Dist: click>=8.3.1
Requires-Dist: fastapi>=0.128.0
Requires-Dist: httpx>=0.28.1
Requires-Dist: loguru>=0.7.3
Requires-Dist: pydantic-settings>=2.12.0
Requires-Dist: pydantic[email]>=2.12.5
Requires-Dist: python-dotenv>=1.2.1
Requires-Dist: python-jose[cryptography]>=3.5.0
Requires-Dist: sqlalchemy[asyncio]>=2.0.46
Requires-Dist: svix-ksuid>=0.6.2
